triku/__init__.py
triku/genutils.py
triku/logg.py
triku/tl/__init__.py
triku/tl/_triku.py
triku/tl/_triku_functions.py
triku/utils/__init__.py
triku/utils/_general_utils.py
triku/utils/_triku_tl_utils.py
triku-2.2.0.dist-info/licenses/LICENSE
triku-2.2.0.dist-info/METADATA
triku-2.2.0.dist-info/WHEEL
triku-2.2.0.dist-info/top_level.txt
triku-2.2.0.dist-info/RECORD
