Metadata-Version: 2.4
Name: triku
Version: 2.2.0
Summary: Feature selection method for Single Cell data.
Author-email: "Alex M. Ascensión" <alexmascension@gmail.com>
License: BSD
Project-URL: repository, https://gitlab.com/alexmascension/triku
Classifier: Intended Audience :: Developers
Classifier: Intended Audience :: Science/Research
Classifier: Natural Language :: English
Classifier: Operating System :: MacOS :: MacOS X
Classifier: Operating System :: POSIX :: Linux
Classifier: Programming Language :: Python :: 3
Classifier: Programming Language :: Python :: 3.7
Classifier: Programming Language :: Python :: 3.8
Classifier: Topic :: Scientific/Engineering :: Bio-Informatics
Requires-Python: >=3.8
License-File: LICENSE
Requires-Dist: scipy
Requires-Dist: numpy
Requires-Dist: pandas
Requires-Dist: scanpy
Requires-Dist: cython
Requires-Dist: tqdm
Requires-Dist: bottleneck
Dynamic: license-file
